README.rst
setup.py
eric_py_demos/__init__.py
eric_py_demos/command_lines.py
eric_py_demos/hello_world.py
eric_py_demos1.egg-info/PKG-INFO
eric_py_demos1.egg-info/SOURCES.txt
eric_py_demos1.egg-info/dependency_links.txt
eric_py_demos1.egg-info/entry_points.txt
eric_py_demos1.egg-info/requires.txt
eric_py_demos1.egg-info/top_level.txt