Metadata-Version: 1.0
Name: eric-py-demos1
Version: 1.0
Summary: setuptools demos
Home-page: http://hustcsxg.github.io
Author: dn_eric
Author-email: hustcsxg@163.com
License: MIT
Platform: UNKNOWN
